izy/__init__.py
izy/__version__.py
izy/bidict.py
izy/decorators.py
izy/discovery.py
izy/misc.py
izy/path.py
izy/regex.py
izy/scorer.py
izy/sorting.py
izy/table.py
izy-0.3.0.dist-info/LICENSE
izy-0.3.0.dist-info/METADATA
izy-0.3.0.dist-info/WHEEL
izy-0.3.0.dist-info/top_level.txt
izy-0.3.0.dist-info/RECORD
