Metadata-Version: 2.1
Name: izy
Version: 0.3.0
Summary: Python functions and classes that make it even easier!
Home-page: https://github.com/tabasy/izy
Author: Mohsen Tabasi
Author-email: m.tabasy@gmail.com
License: MIT
Platform: UNKNOWN
Classifier: License :: OSI Approved :: MIT License
Classifier: Programming Language :: Python
Classifier: Programming Language :: Python :: 3
Classifier: Programming Language :: Python :: 3.6
Classifier: Programming Language :: Python :: Implementation :: CPython
Classifier: Programming Language :: Python :: Implementation :: PyPy
Requires-Python: >=3.6.0
License-File: LICENSE
